submit_tool/__init__.py
submit_tool/tool.py
submit_tool-0.2.0.dist-info/LICENSE
submit_tool-0.2.0.dist-info/METADATA
submit_tool-0.2.0.dist-info/WHEEL
submit_tool-0.2.0.dist-info/entry_points.txt
submit_tool-0.2.0.dist-info/top_level.txt
submit_tool-0.2.0.dist-info/RECORD
