Metadata-Version: 2.1
Name: submit_tool
Version: 0.2.0
Summary: A simple tool to cache the configuration files of the commands
Author-email: Zesen <zesenwang2@gmail.com>
Project-URL: Homepage, https://github.com/WangZesen/submit-tool
Project-URL: Issues, https://github.com/WangZesen/submit-tool/issues
Classifier: Programming Language :: Python :: 3
Classifier: License :: OSI Approved :: MIT License
Classifier: Operating System :: OS Independent
Requires-Python: >=3.8
License-File: LICENSE
